README.rst
cgroup_top.py
setup.py
bin/ctop
ctop.egg-info/PKG-INFO
ctop.egg-info/SOURCES.txt
ctop.egg-info/dependency_links.txt
ctop.egg-info/top_level.txt