Metadata-Version: 1.1
Name: ctop
Version: 1.0.0
Summary: A lightweight top like monitor for linux CGroups
Home-page: https://github.com/yadutaf/ctop
Author: Jean-Tiare Le Bigot
Author-email: jt@yadutaf.fr
License: MIT
Platform: any
Classifier: Environment :: Console
Classifier: Environment :: Console :: Curses
Classifier: Development Status :: 5 - Production/Stable
Classifier: Intended Audience :: Developers
Classifier: Intended Audience :: System Administrators
Classifier: Topic :: System :: Monitoring
Classifier: License :: OSI Approved :: MIT License
Classifier: Programming Language :: Python :: 2.6
Classifier: Programming Language :: Python :: 2.7
Classifier: Programming Language :: Python :: 3
